interscellar/__init__.py
interscellar/api/__init__.py
interscellar/api/wrapper_2d.py
interscellar/api/wrapper_3d.py
interscellar/core/__init__.py
interscellar/core/compute_interscellar_volumes_3d.py
interscellar/core/find_cell_neighbors_2d.py
interscellar/core/find_cell_neighbors_3d.py
interscellar/visualization/__init__.py
interscellar/visualization/visualize_all_3d.py
interscellar/visualization/visualize_pair_3d.py
interscellar-0.1.0.dist-info/licenses/LICENSE
interscellar-0.1.0.dist-info/METADATA
interscellar-0.1.0.dist-info/WHEEL
interscellar-0.1.0.dist-info/entry_points.txt
interscellar-0.1.0.dist-info/top_level.txt
interscellar-0.1.0.dist-info/RECORD
