Metadata-Version: 2.4
Name: InterSCellar
Version: 0.1.0
Summary: Surface-based Cell Neighbor Detection and Interscellar Volume Computation for 2D & 3D Spatial Omics
Author-email: Eunice Yewon Lee <yl888@duke.edu>
License: MIT
Project-URL: Homepage, https://github.com/euniceyl/InterSCellar
Project-URL: Repository, https://github.com/euniceyl/InterSCellar
Project-URL: Issues, https://github.com/euniceyl/InterSCellar/issues
Keywords: spatial-omics,cell-neighbors,cell-interactions,cell-cell-communication,intercellular,single-cell,transcriptomics,proteomics,metabolomics,bioinformatics,computational-biology,visualization,3d
Classifier: Development Status :: 3 - Alpha
Classifier: Intended Audience :: Science/Research
Classifier: License :: OSI Approved :: MIT License
Classifier: Operating System :: OS Independent
Classifier: Programming Language :: Python :: 3
Classifier: Programming Language :: Python :: 3.8
Classifier: Programming Language :: Python :: 3.9
Classifier: Programming Language :: Python :: 3.10
Classifier: Programming Language :: Python :: 3.11
Classifier: Topic :: Scientific/Engineering :: Bio-Informatics
Requires-Python: >=3.8
License-File: LICENSE
Requires-Dist: numpy>=1.20.0
Requires-Dist: pandas>=1.3.0
Requires-Dist: scipy>=1.7.0
Requires-Dist: tqdm>=4.62.0
Requires-Dist: opencv-python>=4.5.0
Requires-Dist: dask[array]>=2021.0.0
Requires-Dist: matplotlib>=3.4.0
Requires-Dist: scikit-image>=0.18.0
Requires-Dist: seaborn>=0.11.0
Requires-Dist: napari>=0.4.0
Requires-Dist: zarr>=2.10.0
Requires-Dist: anndata>=0.8.0
Requires-Dist: duckdb>=0.6.0
Provides-Extra: anndata
Requires-Dist: anndata>=0.8.0; extra == "anndata"
Provides-Extra: duckdb
Requires-Dist: duckdb>=0.6.0; extra == "duckdb"
Provides-Extra: all
Requires-Dist: anndata>=0.8.0; extra == "all"
Requires-Dist: duckdb>=0.6.0; extra == "all"
Dynamic: license-file
